mia_processes/__init__.py
mia_processes/info.py
mia_processes/process_matlab.py
mia_processes/bricks/__init__.py
mia_processes/bricks/preprocess/__init__.py
mia_processes/bricks/preprocess/afni/__init__.py
mia_processes/bricks/preprocess/afni/processes.py
mia_processes/bricks/preprocess/ants/__init__.py
mia_processes/bricks/preprocess/ants/processes.py
mia_processes/bricks/preprocess/dipy/__init__.py
mia_processes/bricks/preprocess/dipy/processes.py
mia_processes/bricks/preprocess/freesurfer/__init__.py
mia_processes/bricks/preprocess/freesurfer/processes.py
mia_processes/bricks/preprocess/fsl/__init__.py
mia_processes/bricks/preprocess/fsl/processes.py
mia_processes/bricks/preprocess/matlab_wrap/__init__.py
mia_processes/bricks/preprocess/matlab_wrap/processes.py
mia_processes/bricks/preprocess/mrtrix/__init__.py
mia_processes/bricks/preprocess/mrtrix/processes.py
mia_processes/bricks/preprocess/others/__init__.py
mia_processes/bricks/preprocess/others/processing.py
mia_processes/bricks/preprocess/spm/__init__.py
mia_processes/bricks/preprocess/spm/spatial_preprocessing.py
mia_processes/bricks/preprocess/volbrain/__init__.py
mia_processes/bricks/preprocess/volbrain/processes.py
mia_processes/bricks/reports/__init__.py
mia_processes/bricks/reports/processes.py
mia_processes/bricks/reports/reporting.py
mia_processes/bricks/stat/__init__.py
mia_processes/bricks/stat/spm/__init__.py
mia_processes/bricks/stat/spm/model.py
mia_processes/bricks/tools/__init__.py
mia_processes/bricks/tools/tools.py
mia_processes/pipelines/__init__.py
mia_processes/pipelines/CerebVascularReact/__init__.py
mia_processes/pipelines/CerebVascularReact/co2_inhalation.py
mia_processes/pipelines/DWITractography/__init__.py
mia_processes/pipelines/DWITractography/dwi_whole_brain_tractography.py
mia_processes/pipelines/FunctionalLangageMemory/__init__.py
mia_processes/pipelines/FunctionalLangageMemory/ge2rec.py
mia_processes/pipelines/FunctionalLangageMemory/ge2rec_without_behavioural_data.py
mia_processes-2.7.0.dist-info/licenses/LICENSE
mia_processes-2.7.0.dist-info/METADATA
mia_processes-2.7.0.dist-info/WHEEL
mia_processes-2.7.0.dist-info/top_level.txt
mia_processes-2.7.0.dist-info/RECORD
