Metadata-Version: 2.4
Name: mia_processes
Version: 2.7.0
Summary: mia_processes
Home-page: http://populse.github.io/mia_processes
Author: Populse team
Author-email: Populse team <populse-support@univ-grenoble-alpes.fr>
License: CeCILL-B
Project-URL: homepage, http://populse.github.io/mia_processes/
Project-URL: repository, https://github.com/populse/mia_processes
Platform: OS Independent
Classifier: Development Status :: 5 - Production/Stable
Classifier: Environment :: Console
Classifier: Intended Audience :: Developers
Classifier: License :: OSI Approved
Classifier: Natural Language :: English
Classifier: Operating System :: OS Independent
Classifier: Programming Language :: Python :: 3 :: Only
Classifier: Programming Language :: Python :: 3.9
Classifier: Programming Language :: Python :: 3.10
Classifier: Programming Language :: Python :: 3.11
Classifier: Topic :: Software Development :: Libraries :: Python Modules
Requires-Python: >=3.9
License-File: LICENSE
Requires-Dist: boto
Requires-Dist: cmp
Requires-Dist: cfflib
Requires-Dist: dipy
Requires-Dist: nibabel
Requires-Dist: nilearn
Requires-Dist: nipy
Requires-Dist: nipype
Requires-Dist: nitime
Requires-Dist: nitransforms
Requires-Dist: niworkflows
Requires-Dist: numpy
Requires-Dist: openpyxl
Requires-Dist: paramiko
Requires-Dist: populse-db<3.0.0,>=2.5.0
Requires-Dist: populse_mia<3.0.0,>=2.5.0
Requires-Dist: pyxnat
Requires-Dist: reportlab
Requires-Dist: scipy
Requires-Dist: statsmodels
Requires-Dist: templateflow
Requires-Dist: torch
Requires-Dist: vtk
Provides-Extra: doc
Requires-Dist: sphinx>=1.0; extra == "doc"
Dynamic: author
Dynamic: home-page
Dynamic: license-file
Dynamic: platform
